constants.py
enums.py
interfaces.py
utils.py
classes/api_service.py
classes/contracts.py
classes/firefly_client_ll.py
classes/onboarding_signer.py
classes/order_signer.py
classes/signer.py
classes/sockets.py
firefly_client_ll-0.0.1.dist-info/METADATA
firefly_client_ll-0.0.1.dist-info/WHEEL
firefly_client_ll-0.0.1.dist-info/top_level.txt
firefly_client_ll-0.0.1.dist-info/RECORD
