Metadata-Version: 2.1
Name: firefly_client_ll
Version: 0.0.1
Summary: Library to interact with firefly api gateway
